notipy/__init__.py
notipy/messaging.py
notipy_line/__init__.py
notipy_line/py.typed
notipy_line-0.2.1.dist-info/LICENSE
notipy_line-0.2.1.dist-info/METADATA
notipy_line-0.2.1.dist-info/WHEEL
notipy_line-0.2.1.dist-info/top_level.txt
notipy_line-0.2.1.dist-info/RECORD
