Metadata-Version: 2.1
Name: notipy-line
Version: 0.2.1
Summary: Minimal LINE Messaging API pusher for Python
Author-email: Perth <unknown@example.com>
License: MIT
Project-URL: Homepage, https://example.com/notipy-line
Project-URL: Repository, https://example.com/notipy-line
Keywords: LINE,Messaging API,notifications,push
Classifier: Programming Language :: Python :: 3
Classifier: License :: OSI Approved :: MIT License
Classifier: Operating System :: OS Independent
Requires-Python: >=3.8
License-File: LICENSE
Requires-Dist: requests >=2.28
